astana_hub/__init__.py
astana_hub/parser.py
astana_hub-0.0.2.dist-info/LICENSE.txt
astana_hub-0.0.2.dist-info/METADATA
astana_hub-0.0.2.dist-info/WHEEL
astana_hub-0.0.2.dist-info/top_level.txt
astana_hub-0.0.2.dist-info/RECORD
